{
  "timestamp": "2025-08-17T15:19:51.729Z",
  "duration": 1131,
  "results": {
    "stripe": {
      "success": false,
      "error": "Stripe sync failed: Internal Server Error"
    },
    "campaigns": {
      "success": true,
      "count": 2
    },
    "donations": {
      "success": true,
      "count": 4
    },
    "analytics": {
      "success": false,
      "error": "Unexpected token 'I', \"Internal S\"... is not valid JSON"
    },
    "webhooks": {
      "success": true,
      "processed": 0
    }
  },
  "stats": {
    "totalSyncs": 303,
    "successfulSyncs": 303,
    "errors": 0,
    "lastError": null
  },
  "summary": {
    "successful": 3,
    "failed": 2,
    "total": 5
  }
}